digital_ocean_cluster/__init__.py
digital_ocean_cluster/build_wheel.py
digital_ocean_cluster/cluster.py
digital_ocean_cluster/download_doctl.py
digital_ocean_cluster/droplet.py
digital_ocean_cluster/droplet_manager.py
digital_ocean_cluster/ensure_doctl.py
digital_ocean_cluster/locked_print.py
digital_ocean_cluster/machines.py
digital_ocean_cluster/settings.py
digital_ocean_cluster/types.py
digital_ocean_cluster/assets/example.txt
digital_ocean_cluster-1.1.18.dist-info/LICENSE
digital_ocean_cluster-1.1.18.dist-info/METADATA
digital_ocean_cluster-1.1.18.dist-info/WHEEL
digital_ocean_cluster-1.1.18.dist-info/top_level.txt
digital_ocean_cluster-1.1.18.dist-info/RECORD
