Metadata-Version: 2.2
Name: digital-ocean-cluster
Version: 1.1.18
Summary: digital ocean cluster management through droplets
Home-page: https://github.com/zackees/digital-ocean-cluster
Maintainer: Zachary Vorhies
License: BSD 3-Clause License
Keywords: template-python-cmd
Classifier: Programming Language :: Python :: 3
Requires-Python: >=3.10
License-File: LICENSE
Requires-Dist: download
Requires-Dist: appdirs
Requires-Dist: wheel
Requires-Dist: python-dotenv
Dynamic: home-page
Dynamic: maintainer
